networkunit/VERSION
networkunit/__init__.py
networkunit/utils.py
networkunit/capabilities/ProducesSpikeTrains.py
networkunit/capabilities/__init__.py
networkunit/capabilities/.ipynb_checkpoints/ProducesSpikeTrains-checkpoint.py
networkunit/models/__init__.py
networkunit/models/loaded_spiketrains.py
networkunit/models/nest_simulation.py
networkunit/models/stochastic_activity.py
networkunit/models/.ipynb_checkpoints/loaded_spiketrains-checkpoint.py
networkunit/models/.ipynb_checkpoints/stochastic_activity-checkpoint.py
networkunit/models/backends/__init__.py
networkunit/models/backends/nest.py
networkunit/models/backends/storage.py
networkunit/plots/__init__.py
networkunit/plots/correlation_matrix.py
networkunit/plots/covar_pdf.py
networkunit/plots/covar_pdf_ei.py
networkunit/plots/eigenvalues.py
networkunit/plots/eigenvector_loads.py
networkunit/plots/mu_std_table.py
networkunit/plots/power_spectral_density.py
networkunit/plots/rasterplot.py
networkunit/plots/sample_histogram.py
networkunit/scores/__init__.py
networkunit/scores/best_effect_size.py
networkunit/scores/effect_size.py
networkunit/scores/eigenangle.py
networkunit/scores/kl_divergence.py
networkunit/scores/ks_distance.py
networkunit/scores/levene_score.py
networkunit/scores/mwu_statistic.py
networkunit/scores/students_t.py
networkunit/scores/wasserstein_distance.py
networkunit/tests/__init__.py
networkunit/tests/avg_std_correlation_test.py
networkunit/tests/correlation_dist_test.py
networkunit/tests/correlation_matrix_test.py
networkunit/tests/correlation_test.py
networkunit/tests/covariance_test.py
networkunit/tests/eigenvalue_test.py
networkunit/tests/firing_rate_test.py
networkunit/tests/freqband_power_test.py
networkunit/tests/generalized_correlation_matrix_test.py
networkunit/tests/graph_centrality_helperclass.py
networkunit/tests/isi_variation_test.py
networkunit/tests/joint_test.py
networkunit/tests/power_spectrum_test.py
networkunit/tests/timescale_test.py
networkunit/tests/two_sample_test.py
networkunit-0.2.2.dist-info/entry_points.txt
networkunit-0.2.2.dist-info/WHEEL
networkunit-0.2.2.dist-info/METADATA
networkunit-0.2.2.dist-info/RECORD
