Metadata-Version: 2.1
Name: networkunit
Version: 0.2.2
Summary: A SciUnit library for validation testing of spiking networks.
Author-email: NetworkUnit authors and contributors <robin.gutzen@outlook.com>
Requires-Python: >=3.8
Requires-Dist: sciunit >= 0.2.8
Requires-Dist: elephant >= 0.7.0
Requires-Dist: neo >= 0.9
Requires-Dist: networkx >= 2.1
Requires-Dist: tabulate >= 0.8.2
Requires-Dist: seaborn >= 0.8.1
Requires-Dist: numpy >= 1.15.3
Requires-Dist: opencv-python
Requires-Dist: black ; extra == "dev"
Requires-Dist: bump2version ; extra == "dev"
Requires-Dist: flake8 ; extra == "dev"
Requires-Dist: mypy ; extra == "dev"
Requires-Dist: pre-commit ; extra == "dev"
Requires-Dist: pydocstyle ; extra == "dev"
Requires-Dist: pylint ; extra == "dev"
Requires-Dist: pytest ; extra == "dev"
Requires-Dist: pytest-black ; extra == "dev"
Requires-Dist: pytest-cov ; extra == "dev"
Requires-Dist: pytest-flake8 ; extra == "dev"
Requires-Dist: pytest-mypy ; extra == "dev"
Requires-Dist: pytest-pydocstyle ; extra == "dev"
Requires-Dist: pytest-pylint ; extra == "dev"
Requires-Dist: pytest-xdist ; extra == "dev"
Requires-Dist: sphinx ; extra == "doc"
Requires-Dist: sphinx-autodoc-typehints ; extra == "doc"
Requires-Dist: numpydoc>=1.1.0 ; extra == "doc"
Requires-Dist: sphinx-tabs>=1.3.0 ; extra == "doc"
Requires-Dist: sphinx-argparse>=0.4.0 ; extra == "doc"
Requires-Dist: pygments ; extra == "doc"
Requires-Dist: recommonmark ; extra == "doc"
Project-URL: Bug Tracker, https://github.com/INM-6/networkunit/issues
Project-URL: Homepage, https://github.com/INM-6/networkunit
Provides-Extra: dev
Provides-Extra: doc
